acmeasync/__init__.py
acmeasync/__main__.py
acmeasync/acmele.py
acmeasync/certbot2.py
acmeasync/jws.py
acmeasync/proxyserver.py
acmeasync/util.py
acmeasync-0.1.6a0.dist-info/LICENSE.txt
acmeasync-0.1.6a0.dist-info/METADATA
acmeasync-0.1.6a0.dist-info/WHEEL
acmeasync-0.1.6a0.dist-info/entry_points.txt
acmeasync-0.1.6a0.dist-info/top_level.txt
acmeasync-0.1.6a0.dist-info/RECORD
