Metadata-Version: 2.1
Name: acmeasync
Version: 0.1.6a0
Summary: ACME v2 Client using asyncio
Home-page: https://github.com/GothAck/pyacmele
Author: Greg "GothAck " Miell
Author-email: acmeasync@greg.gothack.ninja
License: MIT
Keywords: letsencrypt acme proxy
Platform: UNKNOWN
Classifier: Programming Language :: Python :: 3
Classifier: License :: OSI Approved :: MIT License
Classifier: Operating System :: OS Independent
Requires-Python: >=3.7
Requires-Dist: acme
Requires-Dist: aiohttp
Requires-Dist: aiohttp-requests
